AUTHORS.rst
CONTRIBUTING.rst
HISTORY.rst
LICENSE
MANIFEST.in
README.rst
requirements.txt
setup.py
bash_quote/__init__.py
bash_quote/bash_quote.py
bash_quote.egg-info/PKG-INFO
bash_quote.egg-info/SOURCES.txt
bash_quote.egg-info/dependency_links.txt
bash_quote.egg-info/entry_points.txt
bash_quote.egg-info/not-zip-safe
bash_quote.egg-info/requires.txt
bash_quote.egg-info/top_level.txt