Metadata-Version: 1.1
Name: bash-quote
Version: 1.0.1
Summary: Browse quotes on bash.org from the comfort of your shell.
Home-page: https://github.com/ruairif/bash_quote
Author: Ruairi Fahy
Author-email: ruairifahy91@gmail.com
License: BSD
Keywords: bash_quote
Platform: UNKNOWN
Classifier: Development Status :: 5 - Production/Stable
Classifier: Intended Audience :: Developers
Classifier: License :: OSI Approved :: BSD License
Classifier: Natural Language :: English
Classifier: Programming Language :: Python :: 2
Classifier: Programming Language :: Python :: 2.7
Classifier: Programming Language :: Python :: 3
Classifier: Programming Language :: Python :: 3.3
